{
   "id":"wenet_echo_v1",
   "name":"Echo",
   "description":"This tasks echo the transaction messages",
   "keywords":[
      "example",
      "test"
   ],
   "transactions":{
      "echo":{
         "type":"object",
         "description":"Send the echo message",
         "properties":{
            "message":{
               "type":"string",
               "description":"The message to echo"
            }
         }
      }
   },
   "callbacks":{
      "echo":{
         "type":"object",
         "properties":{
            "taskId":{
               "type":"string",
               "description":"The identifier of the task"
            },
            "communityId":{
               "type":"string",
               "description":"The identifier of the community"
            },
            "message":{
               "type":"string",
               "description":"The echo message"
            }
         }
      }
   },
   "norms":[
      {
         "whenever":"is_received_created_task()",
         "thenceforth":"wenet_task_manager_add_created_transation()"
      },
      {
         "whenever":"is_received_do_transaction_with_label(Transaction,'echo')",
         "thenceforth":"wenet_task_manager_add_transaction_into_task(Transaction) and get_task_transaction_attributes(Attributes,Transaction) and create_callback_message(Callback,'echo',Attributes) and wenet_service_post_callback(Callback) and wenet_task_manager_add_message_into_transaction(Callback)"
      }
   ]
}